argilla_dataset_manager/__init__.py
argilla_dataset_manager/datasets/__init__.py
argilla_dataset_manager/datasets/settings_manager.py
argilla_dataset_manager/utils/__init__.py
argilla_dataset_manager/utils/argilla_client.py
argilla_dataset_manager/utils/data_loader.py
argilla_dataset_manager/utils/data_processor.py
argilla_dataset_manager/utils/dataset_manager.py
argilla_dataset_manager/utils/logger.py
argilla_dataset_manager-0.1.6.dist-info/METADATA
argilla_dataset_manager-0.1.6.dist-info/WHEEL
argilla_dataset_manager-0.1.6.dist-info/top_level.txt
argilla_dataset_manager-0.1.6.dist-info/RECORD
