Metadata-Version: 2.1
Name: argilla-dataset-manager
Version: 0.1.6
Summary: A tool for managing and uploading datasets to Argilla
Home-page: https://github.com/jordanrburger/argilla_dataset_manager
Author: Jordan Burger
Author-email: jordanrburger@gmail.com
Classifier: Development Status :: 3 - Alpha
Classifier: Intended Audience :: Developers
Classifier: Intended Audience :: Science/Research
Classifier: License :: OSI Approved :: MIT License
Classifier: Operating System :: OS Independent
Classifier: Programming Language :: Python :: 3
Classifier: Programming Language :: Python :: 3.8
Classifier: Programming Language :: Python :: 3.9
Classifier: Programming Language :: Python :: 3.10
Classifier: Topic :: Scientific/Engineering :: Artificial Intelligence
Requires-Python: >=3.8
Requires-Dist: argilla>=1.0.0
Requires-Dist: pandas>=1.0.0
Requires-Dist: python-dotenv>=0.10.0
Requires-Dist: requests>=2.0.0
Requires-Dist: pyyaml>=5.0.0
Requires-Dist: tqdm>=4.0.0
Requires-Dist: types-PyYAML>=5.0.0
Requires-Dist: types-requests>=2.0.0
Requires-Dist: types-tqdm>=4.0.0
Requires-Dist: types-setuptools>=60.0.0
Requires-Dist: pandas-stubs>=1.0.0
Requires-Dist: pytest>=6.0.0
Requires-Dist: pytest-cov>=3.0.0
Requires-Dist: black>=22.0.0
Requires-Dist: isort>=5.0.0
Requires-Dist: mypy>=0.900
